PinaTracker/__init__.py
pinatracker-0.1.0.dist-info/METADATA
pinatracker-0.1.0.dist-info/WHEEL
pinatracker-0.1.0.dist-info/licenses/LICENSE
pinatracker-0.1.0.dist-info/RECORD
