Metadata-Version: 2.4
Name: PinaTracker
Version: 0.1.0
Summary: Библиотека для поиска изображений на экране и клика по ним
Author-email: PinaKot <pinakoteka.cs@gmail.com>
License-File: LICENSE
Classifier: License :: OSI Approved :: MIT License
Classifier: Operating System :: OS Independent
Classifier: Programming Language :: Python :: 3
Requires-Python: >=3.8
Requires-Dist: numpy
Requires-Dist: opencv-python
Requires-Dist: pillow
Requires-Dist: pyautogui
